aperc_osemosys/__init__.py
aperc_osemosys/data_config.yml
aperc_osemosys/emissions_factors.csv
aperc_osemosys/main.py
aperc_osemosys/model_config.yml
aperc_osemosys/osemosys-fast.txt
aperc_osemosys/osemosys-fast_1_0.txt
aperc_osemosys/osemosys_1_0.txt
aperc_osemosys/osemosys_short_1_0.txt
aperc_osemosys/results_config.yml
aperc_osemosys-2021.5.dist-info/AUTHORS.rst
aperc_osemosys-2021.5.dist-info/LICENSE.txt
aperc_osemosys-2021.5.dist-info/METADATA
aperc_osemosys-2021.5.dist-info/WHEEL
aperc_osemosys-2021.5.dist-info/entry_points.txt
aperc_osemosys-2021.5.dist-info/top_level.txt
aperc_osemosys-2021.5.dist-info/RECORD
