Metadata-Version: 2.1
Name: aperc-osemosys
Version: 2021.5
Summary: The APERC Toolkit for Energy Analysis and Modeling.
Home-page: https://github.com/asia-pacific-energy-research-centre/aperc-osemosys
Author: David Wogan
Author-email: david.m.wogan@gmail.com
License: mit
Project-URL: Documentation, https://aperc-osemosys.readthedocs.io/en/latest/
Platform: any
Classifier: Development Status :: 4 - Beta
Classifier: Programming Language :: Python
Requires-Python: >=3.7
Requires-Dist: otoole (==0.10.1b3)
Requires-Dist: colorama (==0.4.4)
Provides-Extra: testing
Requires-Dist: pytest ; extra == 'testing'
Requires-Dist: pytest-cov ; extra == 'testing'
